{
    "imagenes":[
        {
            "tipo": "Jornada-UTN",
            "clasificacion": "Sendero EL Ojoche",
            "descripcion": "Limpieza del sendero",
            "imagen": "https://github.com/yinnis/Volunta-UTN-JSON/blob/main/img/Foto-2.JPG?raw=true"
        },
        {
            "tipo": "Red-UNIVES",
            "clasificacion": "Monumento Nacional Guayabo",
            "descripcion": "Parte del grupo de Voluntariado de la UTN",
            "imagen": "https://github.com/yinnis/Volunta-UTN-JSON/blob/main/img/volunta-utn.jpg?raw=true"
        },
        {
            "tipo": "Jornada-UTN",
            "clasificacion": "Sendero EL Ojoche",
            "descripcion": "Charla sobre plantas ornamentales",
            "imagen": "https://github.com/yinnis/Volunta-UTN-JSON/blob/main/img/Foto-3.JPG?raw=true"
        },
        {
            "tipo": "Jornada-UTN",
            "clasificacion": "Sendero EL Ojoche",
            "descripcion": "Limpieza del sendero",
            "imagen": "https://github.com/yinnis/Volunta-UTN-JSON/blob/main/img/Foto-4.JPG?raw=true"
        },
        {
            "tipo": "Red-UNIVES",
            "clasificacion": "Monumento Nacional Guayabo",
            "descripcion": "Limpieza del sendero",
            "imagen": "https://github.com/yinnis/Volunta-UTN-JSON/blob/main/img/Foto-5.JPG?raw=true"
        },
        {
            "tipo": "Jornada-UTN",
            "clasificacion": "Sendero EL Ojoche",
            "descripcion": "Caminata por el Sendero",
            "imagen": "https://github.com/yinnis/Volunta-UTN-JSON/blob/main/img/Foto-6.jpg?raw=true"
        },
        {
            "tipo": "Jornada-UTN",
            "clasificacion": "Sendero EL Ojoche",
            "descripcion": "Charla sobre distintas especies de 치rboles",
            "imagen": "https://github.com/yinnis/Volunta-UTN-JSON/blob/main/img/Foto-7.jpg?raw=true"
        },
        {
            "tipo": "Jornada-UTN",
            "clasificacion": "Sendero EL Ojoche",
            "descripcion": "Parte del grupo de Voluntariado de la UTN",
            "imagen": "https://github.com/yinnis/Volunta-UTN-JSON/blob/main/img/Foto-12.jpg?raw=true"
        },
        {
            "tipo": "Jornada-UTN",
            "clasificacion": "Sendero EL Ojoche",
            "descripcion": "Charla sobre distintas especies de 치rboles",
            "imagen": "https://github.com/yinnis/Volunta-UTN-JSON/blob/main/img/Foto-9.jpg?raw=true"
        },
        {
            "tipo": "Jornada-UTN",
            "clasificacion": "Sendero EL Ojoche",
            "descripcion": "Siembra de plantas ornamentales",
            "imagen": "https://github.com/yinnis/Volunta-UTN-JSON/blob/main/img/Foto-10.JPG?raw=true"
        },
        {
            "tipo": "Jornada-UTN",
            "clasificacion": "Sendero EL Ojoche",
            "descripcion": "Observarci칩n de tipos de 치rboles",
            "imagen": "https://github.com/yinnis/Volunta-UTN-JSON/blob/main/img/Foto-11.JPG?raw=true"
        },
        {
            "tipo": "Jornada-UTN",
            "clasificacion": "Sendero EL Ojoche",
            "descripcion": "Limpieza del sendero",
            "imagen": "https://github.com/yinnis/Volunta-UTN-JSON/blob/main/img/Foto-8.jpg?raw=true"
        }
        
    ]
}